chess_engines/__init__.py
chess_engines/engines.py
chess_engines/parser/__init__.py
chess_engines/parser/parser.py
chess_engines/parser/gen/__init__.py
chess_engines/parser/gen/pgnLexer.py
chess_engines/parser/gen/pgnListener.py
chess_engines/parser/gen/pgnParser.py
chess_engines/parser/gen/pgnVisitor.py
chessEngines-1.1.1.dist-info/LICENCE
chessEngines-1.1.1.dist-info/METADATA
chessEngines-1.1.1.dist-info/WHEEL
chessEngines-1.1.1.dist-info/top_level.txt
chessEngines-1.1.1.dist-info/RECORD
