Metadata-Version: 2.1
Name: chessEngines
Version: 1.1.1
Summary: A wrapper for chess engines supporting the UCI protocol
Home-page: https://github.com/MarioDiCaprio/chessEngines
Author: Mario Di Caprio
Author-email: mariodicaprio10@gmail.com
License: UNKNOWN
Project-URL: Bug Tracker, https://github.com/MarioDiCaprio/chessEngines/issues
Platform: UNKNOWN
Classifier: Programming Language :: Python :: 3
Classifier: License :: OSI Approved :: MIT License
Classifier: Operating System :: POSIX :: Linux
Requires-Python: >=3.6
License-File: LICENCE
Requires-Dist: antlr4-python3-runtime (==4.9.3)
Requires-Dist: chess (==1.7.0)
